{
  "swagger": "2.0",
  "info": {
    "title": "Challenging API",
    "description": "Daily social challenge API application where the user can develop courage, eliminate social anxiety and lose fear. The challenges will be split into four categories: emotional, physical, intellectual and social challenges.",
    "version": "1.0.0"
  },
  "host": "challenging.onrender.com",
  "basePath": "/",
  "schemes": [
    "https"
  ],
  "paths": {
    "/": {
      "get": {
        "description": "Documentation for the API",
        "responses": {
          "200": {
            "description": "OK"
          }
        }
      }
    },
    "/login": {
      "get": {
        "description": "LOGIN into the API",
        "responses": {
          "default": {
            "description": ""
          }
        }
      }
    },
    "/logout": {
      "get": {
        "description": "LOGOUT of the API",
        "responses": {
          "default": {
            "description": ""
          }
        }
      }
    },
    "/auth/status": {
      "get": {
        "description": "Check if user is logged in the API",
        "responses": {
          "200": {
            "description": "OK"
          },
          "401": {
            "description": "Unauthorized"
          }
        }
      }
    },
    "/users/": {
      "get": {
        "description": "Get all users registered in the API",
        "produces": [
          "application/json"
        ],
        "responses": {
          "200": {
            "description": "OK"
          }
        }
      },
      "post": {
        "description": "Register a user in the API",
        "parameters": [
          {
            "name": "body",
            "in": "body",
            "schema": {
              "type": "object",
              "properties": {
                "username": {
                  "example": "any"
                },
                "categories": {
                  "example": "any"
                },
                "challenges": {
                  "example": "any"
                },
                "githubUrl": {
                  "example": "any"
                },
                "bio": {
                  "example": "any"
                },
                "age": {
                  "example": "any"
                }
              }
            }
          }
        ],
        "responses": {
          "204": {
            "description": "No Content"
          },
          "403": {
            "description": "Forbidden"
          },
          "500": {
            "description": "Internal Server Error"
          }
        }
      }
    },
    "/users/{username}": {
      "get": {
        "description": "Get a user by username",
        "produces": [
          "application/json"
        ],
        "parameters": [
          {
            "name": "username",
            "in": "path",
            "required": true,
            "type": "string"
          }
        ],
        "responses": {
          "200": {
            "description": "OK"
          }
        }
      },
      "put": {
        "description": "Modify a user",
        "parameters": [
          {
            "name": "username",
            "in": "path",
            "required": true,
            "type": "string"
          },
          {
            "name": "body",
            "in": "body",
            "schema": {
              "type": "object",
              "properties": {
                "username": {
                  "example": "any"
                },
                "categories": {
                  "example": "any"
                },
                "challenges": {
                  "example": "any"
                },
                "githubUrl": {
                  "example": "any"
                },
                "bio": {
                  "example": "any"
                },
                "age": {
                  "example": "any"
                }
              }
            }
          }
        ],
        "responses": {
          "204": {
            "description": "No Content"
          },
          "403": {
            "description": "Forbidden"
          },
          "500": {
            "description": "Internal Server Error"
          }
        }
      },
      "delete": {
        "description": "Delete a user",
        "parameters": [
          {
            "name": "username",
            "in": "path",
            "required": true,
            "type": "string"
          }
        ],
        "responses": {
          "204": {
            "description": "No Content"
          },
          "403": {
            "description": "Forbidden"
          },
          "500": {
            "description": "Internal Server Error"
          }
        }
      }
    },
    "/intellectual/": {
      "get": {
        "description": "Get all the lists of intellectual challenges.",
        "produces": [
          "application/json"
        ],
        "responses": {
          "200": {
            "description": "OK"
          }
        }
      },
      "post": {
        "description": "Create a list of intellectual challenges.",
        "parameters": [
          {
            "name": "body",
            "in": "body",
            "schema": {
              "type": "object",
              "properties": {
                "dailyChallenges": {
                  "example": "any"
                },
                "listDifficulty": {
                  "example": "any"
                },
                "title": {
                  "example": "any"
                },
                "description": {
                  "example": "any"
                }
              }
            }
          }
        ],
        "responses": {
          "204": {
            "description": "No Content"
          },
          "403": {
            "description": "Forbidden"
          },
          "500": {
            "description": "Internal Server Error"
          }
        }
      }
    },
    "/intellectual/{listId}": {
      "get": {
        "description": "Get a list of intellectual challenges by ID.",
        "produces": [
          "application/json"
        ],
        "parameters": [
          {
            "name": "listId",
            "in": "path",
            "required": true,
            "type": "string"
          }
        ],
        "responses": {
          "200": {
            "description": "OK"
          }
        }
      },
      "put": {
        "description": "Modify a list of an intellectual challenge.",
        "parameters": [
          {
            "name": "listId",
            "in": "path",
            "required": true,
            "type": "string"
          },
          {
            "name": "body",
            "in": "body",
            "schema": {
              "type": "object",
              "properties": {
                "users": {
                  "example": "any"
                },
                "dailyChallenges": {
                  "example": "any"
                },
                "listDifficulty": {
                  "example": "any"
                },
                "title": {
                  "example": "any"
                },
                "description": {
                  "example": "any"
                }
              }
            }
          }
        ],
        "responses": {
          "204": {
            "description": "No Content"
          },
          "403": {
            "description": "Forbidden"
          },
          "500": {
            "description": "Internal Server Error"
          }
        }
      },
      "delete": {
        "description": "Delete a list of intellectual challenges by ID.",
        "parameters": [
          {
            "name": "listId",
            "in": "path",
            "required": true,
            "type": "string"
          }
        ],
        "responses": {
          "204": {
            "description": "No Content"
          },
          "403": {
            "description": "Forbidden"
          },
          "500": {
            "description": "Internal Server Error"
          }
        }
      }
    },
    "/intellectual/users": {
      "get": {
        "description": "Get all the users from an intellectual list.",
        "produces": [
          "application/json"
        ],
        "responses": {
          "200": {
            "description": "OK"
          }
        }
      }
    },
    "/intellectual/{listId}/{username}": {
      "put": {
        "description": "Modify an intellectual list for a specific user.",
        "parameters": [
          {
            "name": "listId",
            "in": "path",
            "required": true,
            "type": "string"
          },
          {
            "name": "username",
            "in": "path",
            "required": true,
            "type": "string"
          }
        ],
        "responses": {
          "204": {
            "description": "No Content"
          },
          "403": {
            "description": "Forbidden"
          },
          "404": {
            "description": "Not Found"
          },
          "500": {
            "description": "Internal Server Error"
          }
        }
      }
    },
    "/social/": {
      "get": {
        "description": "Get all the lists of social challenges.",
        "produces": [
          "application/json"
        ],
        "responses": {
          "200": {
            "description": "OK"
          }
        }
      },
      "post": {
        "description": "",
        "parameters": [
          {
            "name": "body",
            "in": "body",
            "schema": {
              "type": "object",
              "properties": {
                "dailyChallenges": {
                  "example": "any"
                },
                "listDifficulty": {
                  "example": "any"
                },
                "title": {
                  "example": "any"
                },
                "description": {
                  "example": "any"
                }
              }
            }
          }
        ],
        "responses": {
          "204": {
            "description": "No Content"
          },
          "403": {
            "description": "Forbidden"
          },
          "500": {
            "description": "Internal Server Error"
          }
        }
      }
    },
    "/social/{listId}": {
      "get": {
        "description": "Get a list of social challenges by ID.",
        "produces": [
          "application/json"
        ],
        "parameters": [
          {
            "name": "listId",
            "in": "path",
            "required": true,
            "type": "string"
          }
        ],
        "responses": {
          "200": {
            "description": "OK"
          }
        }
      },
      "put": {
        "description": "",
        "parameters": [
          {
            "name": "listId",
            "in": "path",
            "required": true,
            "type": "string"
          },
          {
            "name": "body",
            "in": "body",
            "schema": {
              "type": "object",
              "properties": {
                "users": {
                  "example": "any"
                },
                "dailyChallenges": {
                  "example": "any"
                },
                "listDifficulty": {
                  "example": "any"
                },
                "title": {
                  "example": "any"
                },
                "description": {
                  "example": "any"
                }
              }
            }
          }
        ],
        "responses": {
          "204": {
            "description": "No Content"
          },
          "403": {
            "description": "Forbidden"
          },
          "500": {
            "description": "Internal Server Error"
          }
        }
      },
      "delete": {
        "description": "",
        "parameters": [
          {
            "name": "listId",
            "in": "path",
            "required": true,
            "type": "string"
          }
        ],
        "responses": {
          "204": {
            "description": "No Content"
          },
          "403": {
            "description": "Forbidden"
          },
          "500": {
            "description": "Internal Server Error"
          }
        }
      }
    },
    "/social/users": {
      "get": {
        "description": "",
        "produces": [
          "application/json"
        ],
        "responses": {
          "200": {
            "description": "OK"
          }
        }
      }
    },
    "/social/{listId}/{username}": {
      "put": {
        "description": "",
        "parameters": [
          {
            "name": "listId",
            "in": "path",
            "required": true,
            "type": "string"
          },
          {
            "name": "username",
            "in": "path",
            "required": true,
            "type": "string"
          }
        ],
        "responses": {
          "204": {
            "description": "No Content"
          },
          "403": {
            "description": "Forbidden"
          },
          "404": {
            "description": "Not Found"
          },
          "500": {
            "description": "Internal Server Error"
          }
        }
      }
    },
    "/emotional/": {
      "get": {
        "description": "Get all the lists of emocional challenges.",
        "produces": [
          "application/json"
        ],
        "responses": {
          "200": {
            "description": "OK"
          }
        }
      },
      "post": {
        "description": "",
        "parameters": [
          {
            "name": "body",
            "in": "body",
            "schema": {
              "type": "object",
              "properties": {
                "dailyChallenges": {
                  "example": "any"
                },
                "listDifficulty": {
                  "example": "any"
                },
                "title": {
                  "example": "any"
                },
                "description": {
                  "example": "any"
                }
              }
            }
          }
        ],
        "responses": {
          "204": {
            "description": "No Content"
          },
          "403": {
            "description": "Forbidden"
          },
          "500": {
            "description": "Internal Server Error"
          }
        }
      }
    },
    "/emotional/{listId}": {
      "get": {
        "description": "Get a list of emotional challenges by ID.",
        "produces": [
          "application/json"
        ],
        "parameters": [
          {
            "name": "listId",
            "in": "path",
            "required": true,
            "type": "string"
          }
        ],
        "responses": {
          "200": {
            "description": "OK"
          }
        }
      },
      "put": {
        "description": "",
        "parameters": [
          {
            "name": "listId",
            "in": "path",
            "required": true,
            "type": "string"
          },
          {
            "name": "body",
            "in": "body",
            "schema": {
              "type": "object",
              "properties": {
                "users": {
                  "example": "any"
                },
                "dailyChallenges": {
                  "example": "any"
                },
                "listDifficulty": {
                  "example": "any"
                },
                "title": {
                  "example": "any"
                },
                "description": {
                  "example": "any"
                }
              }
            }
          }
        ],
        "responses": {
          "204": {
            "description": "No Content"
          },
          "403": {
            "description": "Forbidden"
          },
          "500": {
            "description": "Internal Server Error"
          }
        }
      },
      "delete": {
        "description": "",
        "parameters": [
          {
            "name": "listId",
            "in": "path",
            "required": true,
            "type": "string"
          }
        ],
        "responses": {
          "204": {
            "description": "No Content"
          },
          "403": {
            "description": "Forbidden"
          },
          "500": {
            "description": "Internal Server Error"
          }
        }
      }
    },
    "/emotional/users": {
      "get": {
        "description": "",
        "produces": [
          "application/json"
        ],
        "responses": {
          "200": {
            "description": "OK"
          }
        }
      }
    },
    "/emotional/{listId}/{username}": {
      "put": {
        "description": "",
        "parameters": [
          {
            "name": "listId",
            "in": "path",
            "required": true,
            "type": "string"
          },
          {
            "name": "username",
            "in": "path",
            "required": true,
            "type": "string"
          }
        ],
        "responses": {
          "204": {
            "description": "No Content"
          },
          "403": {
            "description": "Forbidden"
          },
          "404": {
            "description": "Not Found"
          },
          "500": {
            "description": "Internal Server Error"
          }
        }
      }
    },
    "/physical/": {
      "get": {
        "description": "Get all the lists of physical challenges.",
        "produces": [
          "application/json"
        ],
        "responses": {
          "200": {
            "description": "OK"
          }
        }
      },
      "post": {
        "description": "",
        "parameters": [
          {
            "name": "body",
            "in": "body",
            "schema": {
              "type": "object",
              "properties": {
                "dailyChallenges": {
                  "example": "any"
                },
                "listDifficulty": {
                  "example": "any"
                },
                "title": {
                  "example": "any"
                },
                "description": {
                  "example": "any"
                }
              }
            }
          }
        ],
        "responses": {
          "204": {
            "description": "No Content"
          },
          "403": {
            "description": "Forbidden"
          },
          "500": {
            "description": "Internal Server Error"
          }
        }
      }
    },
    "/physical/{listId}": {
      "get": {
        "description": "Get a list of physical challenges by ID.",
        "produces": [
          "application/json"
        ],
        "parameters": [
          {
            "name": "listId",
            "in": "path",
            "required": true,
            "type": "string"
          }
        ],
        "responses": {
          "200": {
            "description": "OK"
          }
        }
      },
      "put": {
        "description": "",
        "parameters": [
          {
            "name": "listId",
            "in": "path",
            "required": true,
            "type": "string"
          },
          {
            "name": "body",
            "in": "body",
            "schema": {
              "type": "object",
              "properties": {
                "users": {
                  "example": "any"
                },
                "dailyChallenges": {
                  "example": "any"
                },
                "listDifficulty": {
                  "example": "any"
                },
                "title": {
                  "example": "any"
                },
                "description": {
                  "example": "any"
                }
              }
            }
          }
        ],
        "responses": {
          "204": {
            "description": "No Content"
          },
          "403": {
            "description": "Forbidden"
          },
          "500": {
            "description": "Internal Server Error"
          }
        }
      },
      "delete": {
        "description": "",
        "parameters": [
          {
            "name": "listId",
            "in": "path",
            "required": true,
            "type": "string"
          }
        ],
        "responses": {
          "204": {
            "description": "No Content"
          },
          "403": {
            "description": "Forbidden"
          },
          "500": {
            "description": "Internal Server Error"
          }
        }
      }
    },
    "/physical/users": {
      "get": {
        "description": "",
        "produces": [
          "application/json"
        ],
        "responses": {
          "200": {
            "description": "OK"
          }
        }
      }
    },
    "/physical/{listId}/{username}": {
      "put": {
        "description": "",
        "parameters": [
          {
            "name": "listId",
            "in": "path",
            "required": true,
            "type": "string"
          },
          {
            "name": "username",
            "in": "path",
            "required": true,
            "type": "string"
          }
        ],
        "responses": {
          "204": {
            "description": "No Content"
          },
          "403": {
            "description": "Forbidden"
          },
          "404": {
            "description": "Not Found"
          },
          "500": {
            "description": "Internal Server Error"
          }
        }
      }
    }
  }
}